cursedutils/__init__.py
cursedutils/__main__.py
cursedutils/cursed.py
cursedutils/death.py
cursedutils/iostreams.py
cursedutils/natural_number_syntax.py
cursedutils/pep_ripoffs.py
cursedutils/wrappers.py
cursedutils-4.2.0.dist-info/LICENSE
cursedutils-4.2.0.dist-info/METADATA
cursedutils-4.2.0.dist-info/WHEEL
cursedutils-4.2.0.dist-info/entry_points.txt
cursedutils-4.2.0.dist-info/top_level.txt
cursedutils-4.2.0.dist-info/RECORD
