Metadata-Version: 2.1
Name: cursedutils
Version: 4.2.0
Summary: Do unholy things to python
Home-page: https://github.com/FluffyTrooper2001/cursedutils
Author: FluffyTrooper2001
Author-email: michaelisaiah01@gmail.com
License: XD License
Platform: UNKNOWN
Classifier: Programming Language :: Python :: 3
Classifier: Programming Language :: Python :: 3.9
